backtesting_pp/__init__.py
backtesting_pp/type1.py
backtesting_pp-0.0.3.dist-info/METADATA
backtesting_pp-0.0.3.dist-info/WHEEL
backtesting_pp-0.0.3.dist-info/top_level.txt
backtesting_pp-0.0.3.dist-info/RECORD
