Metadata-Version: 2.1
Name: backtesting-pp
Version: 0.0.3
Summary: Backtest preprocessing
Home-page: https://www.google.com/
Author: grapeabc1
Author-email: dyifnis@hanmail.net
License: MIT
Platform: UNKNOWN
Requires-Python: >=3
